graphSDK/__init__.py
graphSDK/core/__init__.py
graphSDK/core/blessingstate.py
graphSDK/core/execution.py
graphSDK/core/graph.py
itavalleystudent-0.1.0.dist-info/METADATA
itavalleystudent-0.1.0.dist-info/WHEEL
itavalleystudent-0.1.0.dist-info/top_level.txt
itavalleystudent-0.1.0.dist-info/RECORD
